dyad_app/__init__.py
dyad_app/chat_processor.py
dyad_app/academy/__init__.py
dyad_app/academy/academy_prompt.py
dyad_app/academy/academy_util.py
dyad_app/academy/fetch_academy.py
dyad_app/cli/cli.py
dyad_app/logic/__init__.py
dyad_app/logic/actions.py
dyad_app/logic/apply_code.py
dyad_app/logic/chat_files.py
dyad_app/logic/chat_logic.py
dyad_app/logic/revert_code.py
dyad_app/main/__init__.py
dyad_app/main/reset_for_test_page.py
dyad_app/sandpack/__init__.py
dyad_app/static/favicon.ico
dyad_app/static/logo.png
dyad_app/static/styles.css
dyad_app/static/build/css.worker.js
dyad_app/static/build/css.worker.js.LICENSE.txt
dyad_app/static/build/editor.worker.js
dyad_app/static/build/html.worker.js
dyad_app/static/build/html.worker.js.LICENSE.txt
dyad_app/static/build/index.html
dyad_app/static/build/index.js
dyad_app/static/build/index.js.LICENSE.txt
dyad_app/static/build/json.worker.js
dyad_app/static/build/json.worker.js.LICENSE.txt
dyad_app/static/build/ts.worker.js
dyad_app/static/build/ts.worker.js.LICENSE.txt
dyad_app/static/build/viewer_bundle.html
dyad_app/static/build/viewer_bundle.js
dyad_app/static/build/viewer_bundle.js.LICENSE.txt
dyad_app/static/build/css/font/codicon.dfc1b1db.ttf
dyad_app/static/build/static/css/index.css
dyad_app/static/devicons/c.svg
dyad_app/static/devicons/cplusplus.svg
dyad_app/static/devicons/csharp.svg
dyad_app/static/devicons/css.svg
dyad_app/static/devicons/go.svg
dyad_app/static/devicons/html.svg
dyad_app/static/devicons/java.svg
dyad_app/static/devicons/javascript.svg
dyad_app/static/devicons/kotlin.svg
dyad_app/static/devicons/markdown.svg
dyad_app/static/devicons/mysql.svg
dyad_app/static/devicons/nodejs.svg
dyad_app/static/devicons/php.svg
dyad_app/static/devicons/python.svg
dyad_app/static/devicons/react.svg
dyad_app/static/devicons/ruby.svg
dyad_app/static/devicons/sass.svg
dyad_app/static/devicons/swift.svg
dyad_app/static/devicons/typescript.svg
dyad_app/static/devicons/vue.svg
dyad_app/ui/__init__.py
dyad_app-0.1.7.dist-info/METADATA
dyad_app-0.1.7.dist-info/WHEEL
dyad_app-0.1.7.dist-info/entry_points.txt
dyad_app-0.1.7.dist-info/licenses/LICENSE
dyad_app-0.1.7.dist-info/RECORD
