Metadata-Version: 2.4
Name: dyad_app
Version: 0.1.7
Summary: Add your description here
License-File: LICENSE
Requires-Python: >=3.10
Requires-Dist: click>=8.1.7
Requires-Dist: dyad-core==0.1.7
Requires-Dist: dyad-git==0.1.7
Requires-Dist: flask-sock>=0.7.0
Requires-Dist: mesop>=1.0.0
Requires-Dist: pydantic>=2.9.2
Requires-Dist: werkzeug>=3.1.2
